cohort_analysis/__init__.py
cohort_analysis/accessors.py
cohort_analysis/cohort_metrics.py
cohort_analysis/decorators.py
cohort_analysis/exceptions.py
cohort_analysis-0.1.2.dist-info/LICENSE
cohort_analysis-0.1.2.dist-info/METADATA
cohort_analysis-0.1.2.dist-info/WHEEL
cohort_analysis-0.1.2.dist-info/top_level.txt
cohort_analysis-0.1.2.dist-info/RECORD
