Metadata-Version: 2.1
Name: cohort-analysis
Version: 0.1.2
Summary: A package for calculating cohort metrics from an activity stream and cohorts data table.
Home-page: UNKNOWN
Author: PaddyAlton
Author-email: paddy.alton@apolitical.co
License: MIT
Download-URL: https://github.com/apolitical/cohort-analysis/archive/vv0.1.2.tar.gz
Keywords: cohort,activity,retention
Platform: UNKNOWN
Classifier: Development Status :: 2 - Pre-Alpha
Classifier: Intended Audience :: Developers
Classifier: Topic :: Scientific/Engineering :: Information Analysis
Classifier: License :: OSI Approved :: MIT License
Classifier: Programming Language :: Python :: 3
Requires-Dist: pandas (<2.0,>=1.0.0)
Requires-Dist: pandas-flavor (<1.0,>=0.2.0)
